interfere/__init__.py
interfere/base.py
interfere/cross_validation.py
interfere/interventions.py
interfere/metrics.py
interfere/utils.py
interfere/_methods/average_method.py
interfere/_methods/deep_learning.py
interfere/_methods/reservoir_computer.py
interfere/_methods/sindy.py
interfere/_methods/vector_autoregression.py
interfere/_methods/nixtla_methods/__init__.py
interfere/_methods/nixtla_methods/nixtla_adapter.py
interfere/_methods/nixtla_methods/statsforecast_methods.py
interfere/_methods/nixtla_methods/neuralforecast_methods/__init__.py
interfere/_methods/nixtla_methods/neuralforecast_methods/lstm.py
interfere/_methods/nixtla_methods/neuralforecast_methods/nhits.py
interfere/dynamics/__init__.py
interfere/dynamics/arithmetic_brownian_motion.py
interfere/dynamics/base.py
interfere/dynamics/coupled_map_lattice.py
interfere/dynamics/decoupled_noise_dynamics.py
interfere/dynamics/generative_forecasters.py
interfere/dynamics/geometric_brownian_motion.py
interfere/dynamics/kuramoto.py
interfere/dynamics/lotka_voltera.py
interfere/dynamics/michaelis_menten.py
interfere/dynamics/mutualistic_pop.py
interfere/dynamics/ornstein_uhlenbeck.py
interfere/dynamics/planted_aquarium.py
interfere/dynamics/pyclustering_models.py
interfere/dynamics/quadratic_sdes.py
interfere/dynamics/simple_linear_sdes.py
interfere/dynamics/sis.py
interfere/dynamics/statespace_models.py
interfere/dynamics/wilson_cowan.py
interfere/methods/__init__.py
interfere-1.0.1.dist-info/licenses/LICENSE
tests/sample_models.py
tests/test_base.py
tests/test_cross_validation.py
tests/test_dynamics.py
tests/test_interventions.py
tests/test_methods.py
tests/test_metrics.py
tests/test_rescomp.py
interfere-1.0.1.dist-info/METADATA
interfere-1.0.1.dist-info/WHEEL
interfere-1.0.1.dist-info/top_level.txt
interfere-1.0.1.dist-info/RECORD
