Metadata-Version: 2.4
Name: interfere
Version: 1.0.1
Summary: Predicting how complex systems will respond to interventions.
Author-email: DJ Passey <djpassey@unc.edu>
License: MIT License
Project-URL: Repository, https://github.com/djpasseyjr/interfere
Keywords: complex systems,dynamics,nonlinear,causal inference,machine learning,time series,forecast,intervention
License-File: LICENSE
Requires-Dist: networkx
Requires-Dist: numpy<2
Requires-Dist: optuna
Requires-Dist: pysindy
Requires-Dist: scikit-learn
Requires-Dist: statsmodels
Requires-Dist: typing_extensions
Provides-Extra: methods
Requires-Dist: neuralforecast; extra == "methods"
Requires-Dist: statsforecast; extra == "methods"
Requires-Dist: sktime; extra == "methods"
Provides-Extra: dev
Requires-Dist: neuralforecast; extra == "dev"
Requires-Dist: statsforecast; extra == "dev"
Requires-Dist: pytest; extra == "dev"
Requires-Dist: sdeint; extra == "dev"
Requires-Dist: sktime; extra == "dev"
Dynamic: license-file
